r2papi
