Metadata-Version: 2.1
Name: r2papi
Version: 0.1.2
Summary: High level API on top of r2pipe
Home-page: https://www.radare.org
Author: radare2
Project-URL: Source, https://github.com/radare/radare2-r2papi/
Requires-Dist: r2pipe
